pylogger2azblob/__init__.py
pylogger2azblob/handlers.py
pylogger2azblob-0.1.0.dist-info/LICENSE
pylogger2azblob-0.1.0.dist-info/METADATA
pylogger2azblob-0.1.0.dist-info/WHEEL
pylogger2azblob-0.1.0.dist-info/top_level.txt
pylogger2azblob-0.1.0.dist-info/RECORD
