Metadata-Version: 2.1
Name: pylogger2azblob
Version: 0.1.0
Summary: a Python logging handler, BlobStorageTimedRotatingFileHandler, that extends the functionality of the built-in TimedRotatingFileHandler.
Author: Kazuya Onuki
License: Copyright 2024 KazuyaOnuki
Project-URL: Homepage, https://github.com/KazuOnuki/pylogger2azblob
Keywords: azure blob,logging
Classifier: License :: OSI Approved :: MIT License
Classifier: Operating System :: OS Independent
Classifier: Programming Language :: Python :: 3.12
Requires-Python: >=3.12.0
License-File: LICENSE
Requires-Dist: azure-storage-blob
Requires-Dist: azure-identity
Provides-Extra: dev
Requires-Dist: pytest ; extra == 'dev'
Requires-Dist: build ; extra == 'dev'
Requires-Dist: twine ; extra == 'dev'
